pkg_cs/__init__.py
pkg_cs/mymodule.py
pkg_cs-0.1.0.dist-info/METADATA
pkg_cs-0.1.0.dist-info/WHEEL
pkg_cs-0.1.0.dist-info/top_level.txt
pkg_cs-0.1.0.dist-info/RECORD
